module_that_can_be_imported_directly.py
module_that_can_be_invoked_from_cli.py
module_that_can_invoke_gui_from_cli.py
package_name_to_import_with/__init__.py
package_name_to_import_with/data_using_module.py
package_name_to_import_with/garbage_collection_module.py
package_name_to_import_with/metadata.json
package_name_to_import_with/py.typed
package_name_to_import_with/simplify.py
package_name_to_import_with/calculator_sub_package/__init__.py
package_name_to_import_with/calculator_sub_package/wrapper_module.py
package_name_to_import_with/calculator_sub_package/basics/__init__.py
package_name_to_import_with/calculator_sub_package/basics/utility_module.py
package_name_to_import_with/calculator_sub_package/basics/assumptions/__init__.py
package_name_to_import_with/calculator_sub_package/basics/assumptions/inverses_module.py
package_name_to_import_with/calculator_sub_package/basics/assumptions/operations_module.py
package_name_to_install_with-0.0.5.dist-info/LICENSE.txt
package_name_to_install_with-0.0.5.dist-info/METADATA
package_name_to_install_with-0.0.5.dist-info/WHEEL
package_name_to_install_with-0.0.5.dist-info/entry_points.txt
package_name_to_install_with-0.0.5.dist-info/top_level.txt
package_name_to_install_with-0.0.5.dist-info/RECORD
