Metadata-Version: 2.1
Name: package-name-to-install-with
Version: 0.0.5
Summary: A small example package
Author: Anirban Ray
Author-email: 39331844+yarnabrina@users.noreply.github.com, First Author <first.author@example.com>, Second Author <second.author@example.com>
Maintainer: Anirban Ray
Maintainer-email: 39331844+yarnabrina@users.noreply.github.com, First Maintainer <first.maintainer@example.com>, Second Maintainer <second.maintainer@example.com>
License: mit
Project-URL: Bug Tracker, https://github.com/yarnabrina/learn-python-packaging/issues
Project-URL: Documentation, https://learn-python-packaging.readthedocs.io
Project-URL: Source Code, https://github.com/yarnabrina/learn-python-packaging
Keywords: development,packaging,sample,setuptools
Classifier: Development Status :: 5 - Production/Stable
Classifier: Framework :: Flake8
Classifier: Framework :: Pydantic
Classifier: Framework :: Pytest
Classifier: Framework :: Sphinx
Classifier: Intended Audience :: Developers
Classifier: License :: OSI Approved
Classifier: License :: OSI Approved :: MIT License
Classifier: Operating System :: OS Independent
Classifier: Programming Language :: Python
Classifier: Programming Language :: Python :: 3 :: Only
Classifier: Programming Language :: Python :: 3.10
Classifier: Programming Language :: Python :: 3.11
Classifier: Programming Language :: Python :: 3.12
Classifier: Topic :: Software Development
Classifier: Topic :: Software Development :: Build Tools
Classifier: Topic :: Software Development :: Libraries
Classifier: Topic :: Utilities
Classifier: Typing :: Typed
Requires-Python: <3.13,>=3.10
License-File: LICENSE.txt
Requires-Dist: pydantic <3,>=2.4.2
Requires-Dist: PySimpleGUI <4.61,>=4.60.4
Provides-Extra: all
Requires-Dist: autoflake ; extra == 'all'
Requires-Dist: bandit ; extra == 'all'
Requires-Dist: black ; extra == 'all'
Requires-Dist: blacken-docs ; extra == 'all'
Requires-Dist: build ; extra == 'all'
Requires-Dist: codespell ; extra == 'all'
Requires-Dist: coverage[toml] ; extra == 'all'
Requires-Dist: docformatter[tomli] ; extra == 'all'
Requires-Dist: flake8 ; extra == 'all'
Requires-Dist: furo ; extra == 'all'
Requires-Dist: hypothesis[pytest] ; extra == 'all'
Requires-Dist: interrogate ; extra == 'all'
Requires-Dist: isort ; extra == 'all'
Requires-Dist: mypy ; extra == 'all'
Requires-Dist: nox ; extra == 'all'
Requires-Dist: numpydoc ; extra == 'all'
Requires-Dist: pre-commit ; extra == 'all'
Requires-Dist: pydocstyle[toml] ; extra == 'all'
Requires-Dist: pylint ; extra == 'all'
Requires-Dist: pyproject-fmt ; extra == 'all'
Requires-Dist: pyright ; extra == 'all'
Requires-Dist: pytest ; extra == 'all'
Requires-Dist: pyupgrade ; extra == 'all'
Requires-Dist: Sphinx ; extra == 'all'
Requires-Dist: sphinx-copybutton ; extra == 'all'
Requires-Dist: twine ; extra == 'all'
Requires-Dist: validate-pyproject ; extra == 'all'
Requires-Dist: vulture ; extra == 'all'
Provides-Extra: dev
Requires-Dist: codespell ; extra == 'dev'
Requires-Dist: nox ; extra == 'dev'
Requires-Dist: numpydoc ; extra == 'dev'
Requires-Dist: pre-commit ; extra == 'dev'
Provides-Extra: doc
Requires-Dist: furo ; extra == 'doc'
Requires-Dist: Sphinx ; extra == 'doc'
Requires-Dist: sphinx-copybutton ; extra == 'doc'
Provides-Extra: format
Requires-Dist: autoflake ; extra == 'format'
Requires-Dist: black ; extra == 'format'
Requires-Dist: blacken-docs ; extra == 'format'
Requires-Dist: docformatter[tomli] ; extra == 'format'
Requires-Dist: isort ; extra == 'format'
Requires-Dist: pyproject-fmt ; extra == 'format'
Requires-Dist: pyupgrade ; extra == 'format'
Provides-Extra: lint
Requires-Dist: bandit ; extra == 'lint'
Requires-Dist: flake8 ; extra == 'lint'
Requires-Dist: interrogate ; extra == 'lint'
Requires-Dist: mypy ; extra == 'lint'
Requires-Dist: pydocstyle[toml] ; extra == 'lint'
Requires-Dist: pylint ; extra == 'lint'
Requires-Dist: pyright ; extra == 'lint'
Requires-Dist: validate-pyproject ; extra == 'lint'
Requires-Dist: vulture ; extra == 'lint'
Provides-Extra: release
Requires-Dist: build ; extra == 'release'
Requires-Dist: twine ; extra == 'release'
Provides-Extra: test
Requires-Dist: coverage[toml] ; extra == 'test'
Requires-Dist: hypothesis[pytest] ; extra == 'test'
Requires-Dist: pytest ; extra == 'test'
